<?xml version="1.0" encoding="UTF-8"?><record_update table="ua_table_licensing_config">
    <ua_table_licensing_config action="INSERT_OR_UPDATE">
        <is_fulfillment>false</is_fulfillment>
        <license_condition/>
        <license_model>none</license_model>
        <license_roles/>
        <name>x_issas_gesti_n_0_cv</name>
        <op_delete>true</op_delete>
        <op_insert>true</op_insert>
        <op_update>true</op_update>
        <owner_condition/>
        <sys_class_name>ua_table_licensing_config</sys_class_name>
        <sys_created_by>ecsunahata</sys_created_by>
        <sys_created_on>2022-03-08 20:40:05</sys_created_on>
        <sys_id>d8c8147a1b42811084023158cc4bcb9c</sys_id>
        <sys_mod_count>0</sys_mod_count>
        <sys_name>x_issas_gesti_n_0_cv</sys_name>
        <sys_package display_value="Gestión de Oportunidades" source="x_issas_gesti_n_0">e6fcd7aedb86c110f7265eea4b961914</sys_package>
        <sys_policy/>
        <sys_scope display_value="Gestión de Oportunidades">e6fcd7aedb86c110f7265eea4b961914</sys_scope>
        <sys_update_name>ua_table_licensing_config_d8c8147a1b42811084023158cc4bcb9c</sys_update_name>
        <sys_updated_by>ecsunahata</sys_updated_by>
        <sys_updated_on>2022-03-08 20:40:05</sys_updated_on>
    </ua_table_licensing_config>
</record_update>
